sma/__init__.py
sma/analyse.py
sma/analyse_cooccurrence.py
sma/analyse_distribution.py
sma/analyse_frontend.py
sma/analyse_linalg.py
sma/analyse_simulate.py
sma/analyse_triangles.py
sma/classify.py
sma/classify_dimotifs.py
sma/draw.py
sma/generate.py
sma/helper.py
sma/io.py
sma/iterate.py
sma/motif_info.py
sma/properties.py
sma/rbridge.py
sma-2.3.3.dist-info/LICENSE
sma-2.3.3.dist-info/METADATA
sma-2.3.3.dist-info/WHEEL
sma-2.3.3.dist-info/top_level.txt
sma-2.3.3.dist-info/RECORD
