Metadata-Version: 2.1
Name: sma
Version: 2.3.3
Summary: Package for analysing social-ecological networks
Home-page: https://gitlab.com/t.seppelt/sesmotifanalyser
Author: Tim Seppelt
Author-email: t.seppelt-dev@posteo.de
License: UNKNOWN
Project-URL: Bug Tracker, https://gitlab.com/t.seppelt/sesmotifanalyser/issues
Project-URL: Documentation, https://gitlab.com/t.seppelt/sesmotifanalyser/raw/master/doc/_build/latex/SESMotifAnalyser.pdf?inline=false
Project-URL: Source Code, https://gitlab.com/t.seppelt/sesmotifanalyser
Platform: UNKNOWN
Classifier: Programming Language :: Python :: 3
Classifier: License :: OSI Approved :: GNU General Public License v3 (GPLv3)
Classifier: Operating System :: OS Independent
Requires-Python: >=3.6
License-File: LICENSE
Requires-Dist: networkx
Requires-Dist: numpy
Requires-Dist: pandas
Requires-Dist: scipy
Provides-Extra: plots
Requires-Dist: matplotlib ; extra == 'plots'
